popparser
