Metadata-Version: 1.1
Name: popparser
Version: 0.1.0.dev2
Summary: The POP parser framework
Home-page: https://github.com/fredokun/popparser
Author: Frederic Peschanski
Author-email: Frederic.Peschanski@lip6.fr
License: MIT
Keywords: parsing development
Platform: UNKNOWN
Classifier: Development Status :: 3 - Alpha
Classifier: Intended Audience :: Developers
Classifier: Topic :: Software Development :: Libraries
Classifier: License :: OSI Approved :: MIT License
Classifier: Programming Language :: Python :: 3
Classifier: Programming Language :: Python :: 3.2
Classifier: Programming Language :: Python :: 3.3
Classifier: Programming Language :: Python :: 3.4
